<?xml version="1.0" encoding="UTF-8"?>
<!DOCTYPE database SYSTEM "Labor1.dtd">
<database>
   <customer>
      <name>John Doe</name>
      <contactInformation>
         <email>john.doe@example.com</email>
         <phone>+1-555-1234</phone>
      </contactInformation>
      <demographics>
         <age>35</age>
         <gender>male</gender>
         <location>New York</location>
      </demographics>
      <purchaseHistory>
         <product>
            <name>Product A</name>
            <price>99.99</price>
            <date>2023-05-07</date>
         </product>
         <product>
            <name>Product B</name>
            <price>49.99</price>
            <date>2023-04-20</date>
         </product>
      </purchaseHistory>
   </customer>
   <campaign>
      <name>Summer Sale</name>
      <goals>Increase sales by 20%</goals>
      <budget>10000</budget>
      <targetAudience>New customers</targetAudience>
      <timeline>
         <start>2023-06-01</start>
         <end>2023-08-31</end>
      </timeline>
   </campaign>
   <analytics>
      <engagementRates>25%</engagementRates>
      <conversionRates>5%</conversionRates>
      <roi>200%</roi>
   </analytics>
   <support>
      <customerInteractions>50</customerInteractions>
      <supportProvided>100%</supportProvided>
   </support>
   <leads>
      <potentialCustomers>1000</potentialCustomers>
      <interestShown>50%</interestShown>
   </leads>
   <highlevel>
      <aggregatedData>Sales by region</aggregatedData>
      <strategicDecisions>Focus on Northeast region</strategicDecisions>
   </highlevel>
   <engagement>
      <openRates>20%</openRates>
      <clickThroughRates>3%</clickThroughRates>
      <engagementMetrics>Number of website visits</engagementMetrics>
   </engagement>
   <retention>
      <customerLoyalty>80%</customerLoyalty>
      <retentionRates>90%</retentionRates>
   </retention>
   <project>
      <objectives>
         <objective>Launch new product line</objective>
         <objective>Increase brand awareness</objective>
      </objectives>
      <deliverables>
         <deliverable>Product brochure</deliverable>
         <deliverable>Website redesign</deliverable>
      </deliverables>
      <timeline>
         <start>2023-03-01</start>
         <end>2023-10-31</end>
      </timeline>
   </project>
   <dataentry>
      <inputProcess>Manual data entry</inputProcess>
      <dataAccuracy>99%</dataAccuracy>
      <dataCompleteness>100%</dataCompleteness>
   </dataentry>
</database>